metalabs_sdk/__init__.py
metalabs_sdk-0.1.1.dist-info/LICENSE
metalabs_sdk-0.1.1.dist-info/METADATA
metalabs_sdk-0.1.1.dist-info/WHEEL
metalabs_sdk-0.1.1.dist-info/top_level.txt
metalabs_sdk-0.1.1.dist-info/RECORD
