Metadata-Version: 2.1
Name: metalabs-sdk
Version: 0.1.1
Summary: SDK for MetaLabs API 
Home-page: https://github.com/JAnnaraj/meta-labs_sdk
Author: Jeffrey Annaraj
Author-email: jannaraj@baffled.dev
License: UNKNOWN
Keywords: metalabs
Platform: UNKNOWN
Classifier: Programming Language :: Python :: 3
Classifier: License :: OSI Approved :: MIT License
Classifier: Operating System :: OS Independent
Requires-Python: >=3.6
Requires-Dist: urllib3
